sped_ecd/__init__.py
sped_ecd/leiaute4/__init__.py
sped_ecd/leiaute4/arquivos.py
sped_ecd/leiaute4/blocos.py
sped_ecd/leiaute4/registros.py
sped_ecd/leiaute5/__init__.py
sped_ecd/leiaute5/arquivos.py
sped_ecd/leiaute5/blocos.py
sped_ecd/leiaute5/registros.py
sped_ecd-0.0.5.dist-info/DESCRIPTION.rst
sped_ecd-0.0.5.dist-info/METADATA
sped_ecd-0.0.5.dist-info/RECORD
sped_ecd-0.0.5.dist-info/WHEEL
sped_ecd-0.0.5.dist-info/metadata.json
sped_ecd-0.0.5.dist-info/top_level.txt
